langchain_ragie/__init__.py
langchain_ragie/ragie_retriever.py
langchain_ragie-0.3.2.dist-info/LICENSE.txt
langchain_ragie-0.3.2.dist-info/METADATA
langchain_ragie-0.3.2.dist-info/WHEEL
langchain_ragie-0.3.2.dist-info/RECORD
