Metadata-Version: 2.1
Name: langchain-ragie
Version: 0.3.2
Summary: Ragie integration for LangChain
Author: Bob Remeika
Author-email: bob@ragie.ai
Requires-Python: >=3.9.2,<4.0
Classifier: Programming Language :: Python :: 3
Classifier: Programming Language :: Python :: 3.10
Classifier: Programming Language :: Python :: 3.11
Classifier: Programming Language :: Python :: 3.12
Requires-Dist: langchain-core (>=0.3,<0.4)
Requires-Dist: ragie (>=1.9.0,<2.0.0)
Requires-Dist: ruff (>=0.11.10,<0.12.0)
